{
    "BattleTestPreset2": {
        "_gdeSchema": "Preset",
        "Party": [
            "Phoenix",
            "MissChain",
            "Hein",
            "Suwako"
        ],
        "PartyBasicSkill": [
            "S_Ilya_1",
            "S_Azar_5",
            "S_TW_Blue_5",
            "S_LucyC_2"
        ],
        "PartySkills": [
            [
                
            ],
            [
                
            ],
            [
                
            ],
            [
                "S_Suwako_0",
                "S_Suwako_0",
                "S_Suwako_0",
                "S_Suwako_0"
            ]
        ],
        "PartyEquip": [
            [
                "WhitePriestCloth"
            ],
            [
                "WhitePriestCloth"
            ],
            [
                "Ilya_Sword_0",
                "Ilya_Sword_1"
            ],
            [
                
            ]
        ]
    }
}