{
    "S_Cylu_R1": {
        "_gdeSchema": "Skill",
        "Category": "null",
        "Particle": "Assets/Cylu/R1/Anime_Cylu_R1.prefab",
        "Rare": true,
        "Target": "self",
        "NODOD": false,
        "NotCount": true,
        "NotChuck": true,
        "HealSkill": false,
        "Disposable": false,
        "NoDrop": false,
        "IgnoreTaunt": false,
        "Except": false,
        "NoBasicSkill": true,
        "Basic": false,
        "Track": false,
        "Fatal": false,
        "EnemyPreview": false,
        "UnknownTarget": false,
        "Name": "把思路反转过来！",
        "User": "Cylu",
        "Description": "查看所有反转系列的稀有技能，并选择其中 1 个技能抽取。",
        "Counting": 99,
        "UseAp": 0,
        "AutoDelete": 1,
        "Image_0": "S_Cylu_R1\\S_Cylu_R1_Image_0.png",
        "Image_1": "S_Cylu_R1\\S_Cylu_R1_Image_1.png",
        "SkillExtended": [
            "BOSSLucy.S_Cylu_R1"
        ]
    }
}