{
    "myKey": "RemiliaScarletLord",
    "myField": "FaceSmallChar",
    "myValues": {
        "path": "RemiliaScarletLord\\RemiliaScarletLordFaceSmallChar.png",
        "offsetMax": {
            "x": 200.735413,
            "y": 130.717224
        },
        "offsetMin": {
            "x": -168.22522,
            "y": -385.519745
        },
        "pivot": {
            "x": 0.450436056,
            "y": 0.7359605
        }
    },
    "MyChangeType": "FaceSmallChar",
    "myKeys": [
        
    ]
}