{
    "S_Cylu_9": {
        "_gdeSchema": "Skill",
        "Category": "null",
        "Particle": "Particle/Lian/Lian_7",
        "Target": "enemy",
        "NotCount": true,
        "NotChuck": false,
        "Name": "西露的决斗",
        "User": "Cylu",
        "Description": "释放时，技能交换次数+1。\r\n为最下方的技能施加灵动/魔动增益。",
        "IgnoreTaunt": false,
        "Effect_Target": "SE_T_S_Cylu_9",
        "UseAp": 1,
        "SkillExtended": [
            "BOSSLucy.S_Cylu_9"
        ],
        "Image_0": "S_Cylu_9\\S_Cylu_9_Image_0.png",
        "Image_1": "S_Cylu_9\\S_Cylu_9_Image_1.png",
        "Rare": false,
        "NoDrop": false
    }
}