{
    "S_Raye_Vector": {
        "_gdeSchema": "Skill",
        "Category": "null",
        "Particle": "Particle/SilverStein/SilverStein_0",
        "Target": "enemy",
        "NotCount": false,
        "IgnoreTaunt": true,
        "Name": "Maneuver - Vector Blast",
        "Track": true,
        "Description": "Gain 2 Skill Exchange. \r\nIf the user has Armory Armed!: delay action by 3. \r\n",
        "UseAp": 2,
        "User": "Raye",
        "NoBasicSkill": true,
        "Fatal": true,
        "Effect_Target": "SE_T_S_Raye_Vector",
        "Image_0": "S_Raye_Vector\\S_Raye_Vector_Image_0.png",
        "Image_1": "S_Raye_Vector\\S_Raye_Vector_Image_1.png",
        "Image_2": "S_Raye_Vector\\S_Raye_Vector_Image_2.png",
        "SkillExtended": [
            "SkyStriker.S_Raye_Vector"
        ],
        "Rare": false,
        "NODOD": false,
        "NotChuck": false,
        "HealSkill": false,
        "Disposable": false,
        "NoDrop": false,
        "Except": false,
        "Basic": false,
        "EnemyPreview": false,
        "UnknownTarget": false
    }
}