{
    "S_HatsuneMiku_11Rare": {
        "_gdeSchema": "Skill",
        "Category": "null",
        "Rare": true,
        "Name": "メルト",
        "Description": "施加&a层<color=#7FFFD4>未来之音</color>(治疗力的100%)。",
        "UseAp": -1,
        "Particle": "Particle/Enemy/PharosHighPriest_0",
        "Target": "ally",
        "User": "HatsuneMiku",
        "Effect_Self": "null",
        "Effect_Target": "SE_T_S_HatsuneMiku_11Rare",
        "NotCount": true,
        "NODOD": false,
        "NotChuck": false,
        "HealSkill": false,
        "Disposable": false,
        "NoDrop": false,
        "IgnoreTaunt": false,
        "Except": false,
        "NoBasicSkill": false,
        "Basic": true,
        "Track": false,
        "Fatal": false,
        "Image_0": "S_HatsuneMiku_11Rare\\S_HatsuneMiku_11Rare_Image_0.png",
        "Image_1": "S_HatsuneMiku_11Rare\\S_HatsuneMiku_11Rare_Image_1.png",
        "Image_2": "S_HatsuneMiku_11Rare\\S_HatsuneMiku_11Rare_Image_2.png",
        "SkillExtended": [
            "HatsuneMiku.S_HatsuneMiku_11Rare"
        ]
    }
}