{
    "BattleTestPreset2": {
        "_gdeSchema": "Preset",
        "Party": [
            "Chrona",
            "Mement",
            "Hein"
        ],
        "PartyBasicSkill": [
            "S_Chrona_2",
            "S_Mement_P",
            "S_Hein_10"
        ],
        "PartySkills": [
            [
                "S_Chrona_3",
                "S_Chrona_1",
                "S_Chrona_1",
                "S_Chrona_8",
                "S_Chrona_9",
                "S_Chrona_4"
            ],
            [
                "S_Lian_1",
                "S_Lian_1",
                "S_Lian_1"
            ],
            [
                
            ]
        ],
        "PartyEquip": [
            [
                "Equip_Chrona"
            ],
            [
                
            ],
            [
                
            ]
        ],
        "LucySkill": [
            "S_Chrona_LucyD"
        ],
        "Level": 1
    }
}